README.md
setup.cfg
setup.py
daub/__init__.py
daub/cli.py
daub/core.py
daub.egg-info/PKG-INFO
daub.egg-info/SOURCES.txt
daub.egg-info/dependency_links.txt
daub.egg-info/entry_points.txt
daub.egg-info/requires.txt
daub.egg-info/top_level.txt
daub/css/base.css
daub/html/template.html