Metadata-Version: 2.1
Name: daub
Version: 0.2.1
Summary: opinionated release notes generation
Home-page: https://github.com/verillious/daub
Author: William Christian
License: CC0 1.0 universal
Keywords: markdown,cli,pdf,pdf-generation
Platform: UNKNOWN
Classifier: License :: CC0 1.0 Universal (CC0 1.0) Public Domain Dedication
Classifier: Intended Audience :: Developers
Classifier: Operating System :: OS Independent
Classifier: Programming Language :: Python
